bumbo/__init__.py
bumbo/api.py
bumbo/middleware.py
bumbo/orm.py
bumbo/response.py
bumbo_leo-0.0.3.dist-info/METADATA
bumbo_leo-0.0.3.dist-info/WHEEL
bumbo_leo-0.0.3.dist-info/top_level.txt
bumbo_leo-0.0.3.dist-info/RECORD
